exchangecleaning/DataBody.py
exchangecleaning/Ip2Region.py
exchangecleaning/Preprocessing.py
exchangecleaning/__init__.py
exchangecleaning/exchange_clean.py
exchangecleaning/header.py
exchangecleaning/transform.py
exchangecleaning/huobi/__init__.py
exchangecleaning/huobi/handle_huobi.py
exchangecleaning/huobi/transform_huobi.py
exchangecleaning-1.0.0.dist-info/METADATA
exchangecleaning-1.0.0.dist-info/WHEEL
exchangecleaning-1.0.0.dist-info/top_level.txt
exchangecleaning-1.0.0.dist-info/RECORD
